[
    {
        "name": "Introduction to Biology",
        "description": "An introductory course in the field of Biology.",
        "prerequisites": []
    },
    {
        "name": "Cell Biology",
        "description": "A course in the study of cells.",
        "prerequisites": ["Introduction to Biology"]
    },
    {
        "name": "Molecular Genetics",
        "description": "A course in the study of genetics at the molecular level.",
        "prerequisites": ["Introduction to Biology", "Cell Biology"]
    },
    {
        "name": "Neurobiology",
        "description": "A course in the study of the nervous system.",
        "prerequisites": ["Introduction to Biology", "Cell Biology", "Molecular Genetics"]
    }
]