[
  {
    "id": "dnyuvp7ymdbioajio6ar406c",
    "source": "clggtsotk0004p0eqk2lfm793",
    "target": "zrqnyjntpa3cbyc0b66cjglq"
  },
  {
    "id": "dpahj1k005cy7u3cwa0jfd7b",
    "source": "clggtsotk0004p0eqk2lfm793",
    "target": "ovr8ku7wllxdqty01ovhmjre"
  },
  {
    "id": "i64mzp2mopocs2pdxlw1ia8c",
    "source": "clggtsotk0004p0eqk2lfm793",
    "target": "tsnn44wkim179hq4fgtag0ta"
  },
  {
    "id": "y33sc0dkmdr16xsyox0fap66",
    "source": "zrqnyjntpa3cbyc0b66cjglq",
    "target": "xsaejwa8wdmy7wapo1zrcr8k"
  },
  {
    "id": "cuibidv2wksbjfbep42btxx1",
    "source": "zrqnyjntpa3cbyc0b66cjglq",
    "target": "k3wdwzkyg0pmlvmxd38onmzk"
  },
  {
    "id": "ncnip6dxsvb2acur8hert0zt",
    "source": "zrqnyjntpa3cbyc0b66cjglq",
    "target": "ec1n63r2mfaqh8b26a1vcelk"
  },
  {
    "id": "nw1swdc6lbjgnmbb4cj66d4t",
    "source": "zrqnyjntpa3cbyc0b66cjglq",
    "target": "qekgdk1s8cfdty03pb7g1ozv"
  },
  {
    "id": "alao8uafyxo3ix00kwtmuaiu",
    "source": "zrqnyjntpa3cbyc0b66cjglq",
    "target": "uncci3ccl7jxxo4lb6w46xq0"
  },
  {
    "id": "xd8jkt6fwkza92ovib9la3ih",
    "source": "zrqnyjntpa3cbyc0b66cjglq",
    "target": "putci5121bht0urqrvqye8v8"
  },
  {
    "id": "eje0sp8mj1o8ht42heurmirx",
    "source": "zrqnyjntpa3cbyc0b66cjglq",
    "target": "er5u1sytmk5mra3zxqkz7m04"
  },
  {
    "id": "rb744u3z7pldzudm001z23d1",
    "source": "zrqnyjntpa3cbyc0b66cjglq",
    "target": "flya2woud0efqd3bwqjmdj3a"
  },
  {
    "id": "ecvqawoz4dqfo37otm38o7j5",
    "source": "zrqnyjntpa3cbyc0b66cjglq",
    "target": "e32e39d4ziajkxjrirkcutbz"
  },
  {
    "id": "szi2f3fber524g9qqgidvvzj",
    "source": "zrqnyjntpa3cbyc0b66cjglq",
    "target": "rul85bvivt3yuyyubm5lgu6x"
  },
  {
    "id": "i93cm3uydjbcpi5enmwwqkg2",
    "source": "zrqnyjntpa3cbyc0b66cjglq",
    "target": "clml68dueiflbrlqsu66yxog"
  },
  {
    "id": "jdzirni2sl12ztfls2mezvf9",
    "source": "zrqnyjntpa3cbyc0b66cjglq",
    "target": "gewxxb54cp7cc13guq6u6fvp"
  },
  {
    "id": "xe12q48qqekzs4tqwaq84i03",
    "source": "zrqnyjntpa3cbyc0b66cjglq",
    "target": "szbro05oxcwz1h0acw75hqu4"
  },
  {
    "id": "bawhyxz7i2twmyb692rrrgkn",
    "source": "zrqnyjntpa3cbyc0b66cjglq",
    "target": "hoktowuaz2ksqu5u1pn68xk5"
  },
  {
    "id": "re5w5wt7tai9h6o1vtktllsc",
    "source": "zrqnyjntpa3cbyc0b66cjglq",
    "target": "pjezl7z0bwj0sd2h37d2kx6a"
  },
  {
    "id": "m3o08bqnngxw6qgpykmxqinp",
    "source": "zrqnyjntpa3cbyc0b66cjglq",
    "target": "lvair14y9ta4k08rozqdbp4n"
  },
  {
    "id": "ac90qn2111bx19x4oa1a706w",
    "source": "zrqnyjntpa3cbyc0b66cjglq",
    "target": "vs5ep3ere10vsvl4e0ry9q8i"
  },
  {
    "id": "ilrxe0i5islvgbcjvcwld06l",
    "source": "zrqnyjntpa3cbyc0b66cjglq",
    "target": "byss76qbag3juxn891jkzhb6"
  },
  {
    "id": "h2wmrk7jj3anj409ox831114",
    "source": "zrqnyjntpa3cbyc0b66cjglq",
    "target": "sh44f9rzahk5n4b5hx26rhnl"
  },
  {
    "id": "omlou9b84e76fcppwqt9076o",
    "source": "zrqnyjntpa3cbyc0b66cjglq",
    "target": "tblwwggcjmsyu6j6wiogpc43"
  },
  {
    "id": "yk4baipn209foqd43wpiqe4a",
    "source": "ovr8ku7wllxdqty01ovhmjre",
    "target": "snwkaecnxg9dv4lv97ee3yr4"
  },
  {
    "id": "g8niq3psi6ygknofxbgl24zz",
    "source": "ovr8ku7wllxdqty01ovhmjre",
    "target": "rq79lb334avhoexa0l2mscam"
  },
  {
    "id": "i00df0yd9k11ldmdctpenwid",
    "source": "ovr8ku7wllxdqty01ovhmjre",
    "target": "rn075e00it0s7tw7pimd9zzw"
  },
  {
    "id": "kl7iw3kj7q655y4hiwy2y7gh",
    "source": "ovr8ku7wllxdqty01ovhmjre",
    "target": "g1seo751hp6dbe6ykt4ryad8"
  },
  {
    "id": "asotatbirtvzxfqhpy9jynsq",
    "source": "ovr8ku7wllxdqty01ovhmjre",
    "target": "z6ac6k88svgqzics4c0ai7fq"
  },
  {
    "id": "jfqvkdqpbz3lbkbvgjaf8yab",
    "source": "ovr8ku7wllxdqty01ovhmjre",
    "target": "m51f6nr6wliz33mo26bg71pm"
  },
  {
    "id": "sj882qo7xpd9zkic7o4cpnj3",
    "source": "ovr8ku7wllxdqty01ovhmjre",
    "target": "qkllgop6zgwphnytvuhx846f"
  },
  {
    "id": "dcwuo47lxiz5cky2y7r9929e",
    "source": "ovr8ku7wllxdqty01ovhmjre",
    "target": "mcxygzpen8tafg3nutpw42we"
  },
  {
    "id": "r7tzi8p6wyuhhovl5j1yuyas",
    "source": "ovr8ku7wllxdqty01ovhmjre",
    "target": "jvfx5xf1cl4u5xjlkkepbdun"
  },
  {
    "id": "n9ozfrmcl44xc08mtu16d5aj",
    "source": "tsnn44wkim179hq4fgtag0ta",
    "target": "m8ccxojqrzwh12bft0xdczyl"
  },
  {
    "id": "dn2luavgurx3f7lt2b7ylcnz",
    "source": "tsnn44wkim179hq4fgtag0ta",
    "target": "jzc2m7xue2iigskwd4y9t9gn"
  },
  {
    "id": "gzu4s281ac9ahmikzexj7cev",
    "source": "tsnn44wkim179hq4fgtag0ta",
    "target": "qnvngbvws0aklg9fpds6q12r"
  },
  {
    "id": "akjq8z2stioshk0af62gs8r2",
    "source": "tsnn44wkim179hq4fgtag0ta",
    "target": "kbl4fdt7wqzckjqx7oem849y"
  }
]
