{
  "subdisciplines": [
    {
      "name": "Attention",
      "description": "The study of selective attention, divided attention, and other forms of attention.",
      "parent": "Cognitive Psychology",
      "children": {}
    },
    {
      "name": "Memory",
      "description": "The study of short-term memory, long-term memory, and other types of memory.",
      "parent": "Cognitive Psychology",
      "children": {}
    },
    {
      "name": "Perception",
      "description": "The study of how we perceive and make sense of the world around us.",
      "parent": "Cognitive Psychology",
      "children": {}
    },
    {
      "name": "Language",
      "description": "The study of how we acquire, comprehend, and use language.",
      "parent": "Cognitive Psychology",
      "children": {}
    },
    {
      "name": "Problem solving",
      "description": "The study of how we solve problems and make decisions.",
      "parent": "Cognitive Psychology",
      "children": {}
    },
    {
      "name": "Cognitive Neuroscience",
      "description": "The study of how the brain supports cognitive processes through the use of neuroimaging, electrophysiology, and other methods.",
      "parent": "Cognitive Psychology",
      "children": {}
    }
  ]
}