{
  "subdisciplines": [
    {
      "name": "Science Writing",
      "description": "The practice of communicating scientific findings to a general audience through written articles and other media.",
      "parent": "Science Journalism",
      "children": {}
    },
    {
      "name": "Science Editing",
      "description": "The process of reviewing and improving scientific writing for publication.",
      "parent": "Science Journalism",
      "children": {}
    },
    {
      "name": "Science Communication",
      "description": "The dissemination of scientific knowledge to a wider audience, including policy makers, the media, and the general public.",
      "parent": "Science Journalism",
      "children": {}
    }
  ]
}